myspeech/__init__.py
myspeech/core.py
myspeech-0.1.1.dist-info/METADATA
myspeech-0.1.1.dist-info/WHEEL
myspeech-0.1.1.dist-info/top_level.txt
myspeech-0.1.1.dist-info/RECORD
