Metadata-Version: 2.4
Name: myspeech
Version: 0.1.1
Summary: ML and speech lab experiments
Author: Your Name
Requires-Python: >=3.8
Requires-Dist: numpy
Requires-Dist: tensorflow
Requires-Dist: matplotlib
Requires-Dist: speechrecognition
Requires-Dist: pyttsx3
Requires-Dist: pandas
Requires-Dist: scikit-learn
